main_launcher/2048_pygame_with_ai.py
main_launcher/__init__.py
main_launcher/river_crossing.py
main_launcher/assets/2048_display.png
main_launcher/assets/background.png
main_launcher/assets/boat.png
main_launcher/assets/chicken.png
main_launcher/assets/farmer.png
main_launcher/assets/fox.png
main_launcher/assets/grain.png
main_launcher/assets/main_bg.png
main_launcher/assets/audio/btn-clicking-1.wav
main_launcher/assets/audio/btn_hover.wav
2048_river-0.1.8.dist-info/METADATA
2048_river-0.1.8.dist-info/WHEEL
2048_river-0.1.8.dist-info/entry_points.txt
2048_river-0.1.8.dist-info/top_level.txt
2048_river-0.1.8.dist-info/RECORD
