Metadata-Version: 2.4
Name: 2048-river
Version: 0.1.8
Requires-Dist: requests
Requires-Dist: pygame
Dynamic: requires-dist
